.class public newton
.super java/lang/Object

.method public <init>()V
.var 0 is this Lnewton;
aload 0
invokespecial java/lang/Object/<init>()V
return
.limit locals 1
.limit stack 1
.end method

.method public static main([Ljava/lang/String;)V
.var 0 is print Llibrary/print;
.var 1 is read Llibrary/read;
.var 2 is root Lnewton_bin/routine;

new library/print
dup
invokespecial library/print/<init>()V
astore 0
new library/read
dup
invokespecial library/read/<init>()V
astore 1
new routine
dup
invokespecial routine/<init>()V
astore 2
return
.limit locals 3
.limit stack 16
.end method
.class public newton
.super java/lang/Object

.method public <init>()V
.var 0 is this Lnewton;
aload 0
invokespecial java/lang/Object/<init>()V
return
.limit locals 1
.limit stack 1
.end method

.method public static main([Ljava/lang/String;)V
.var 0 is print Llibrary/print;
.var 1 is read Llibrary/read;
.var 2 is root Lnewton_bin/routine;

new library/print
dup
invokespecial library/print/<init>()V
astore 0
new library/read
dup
invokespecial library/read/<init>()V
astore 1
new routine
dup
invokespecial routine/<init>()V
astore 2
return
.limit locals 3
.limit stack 16
.end method
.class public newton
.super java/lang/Object

.method public <init>()V
.var 0 is this Lnewton;
aload 0
invokespecial java/lang/Object/<init>()V
return
.limit locals 1
.limit stack 1
.end method

.method public static main([Ljava/lang/String;)V
.var 0 is print Llibrary/print;
.var 1 is read Llibrary/read;
.var 2 is root Lnewton_bin/routine;

new library/print
dup
invokespecial library/print/<init>()V
astore 0
new library/read
dup
invokespecial library/read/<init>()V
astore 1
new routine
dup
invokespecial routine/<init>()V
astore 2
return
.limit locals 3
.limit stack 16
.end method
.class public newton
.super java/lang/Object

.method public <init>()V
.var 0 is this Lnewton;
aload 0
invokespecial java/lang/Object/<init>()V
return
.limit locals 1
.limit stack 1
.end method

.method public static main([Ljava/lang/String;)V
.var 0 is print Llibrary/print;
.var 1 is read Llibrary/read;
.var 2 is root Lnewton_bin/routine;

new library/print
dup
invokespecial library/print/<init>()V
astore 0
new library/read
dup
invokespecial library/read/<init>()V
astore 1
new routine
dup
invokespecial routine/<init>()V
astore 2
return
.limit locals 3
.limit stack 16
.end method
.class public newton
.super java/lang/Object

.method public <init>()V
.var 0 is this Lnewton;
aload 0
invokespecial java/lang/Object/<init>()V
return
.limit locals 1
.limit stack 1
.end method

.method public static main([Ljava/lang/String;)V
.var 0 is print Llibrary/print;
.var 1 is read Llibrary/read;
.var 2 is root Lnewton_bin/routine;

new library/print
dup
invokespecial library/print/<init>()V
astore 0
new library/read
dup
invokespecial library/read/<init>()V
astore 1
new routine
dup
invokespecial routine/<init>()V
astore 2
return
.limit locals 3
.limit stack 16
.end method
.class public newton
.super java/lang/Object

.method public <init>()V
.var 0 is this Lnewton;
aload 0
invokespecial java/lang/Object/<init>()V
return
.limit locals 1
.limit stack 1
.end method

.method public static main([Ljava/lang/String;)V
.var 0 is print Llibrary/print;
.var 1 is read Llibrary/read;
.var 2 is root Lnewton_bin/routine;

new library/print
dup
invokespecial library/print/<init>()V
astore 0
new library/read
dup
invokespecial library/read/<init>()V
astore 1
new routine
dup
invokespecial routine/<init>()V
astore 2
return
.limit locals 3
.limit stack 16
.end method
